{
  "0": "Euclid",
  "1": "Hilbert Dimension",
  "2": "Calypso",
  "3": "Hesperius Dimension",
  "4": "Hyades",
  "5": "Ickjamatew",
  "6": "Budullangr",
  "7": "Kikolgallr",
  "8": "Eltiensleen",
  "9": "Eissentam",
  "10": "Elkupalos",
  "11": "Aptarkaba",
  "12": "Ontiniangp",
  "13": "Odiwagiri",
  "14": "Ogtialabi",
  "15": "Muhacksonto",
  "16": "Hitonskyer",
  "17": "Rerasmutul",
  "18": "Isdoraijung",
  "19": "Doctinawyra",
  "20": "Loychazinq",
  "21": "Zukasizawa",
  "22": "Ekwathore",
  "23": "Yaboroganh",
  "24": "Psjaneqreb",
  "25": "Tsjeldansen",
  "26": "Ewdraldsk",
  "27": "Lsjsjrwjwgs",
  "28": "Zilsjdhejd",
  "29": "Xsjvbdksjv",
  "30": "Tjsjsvfnsl",
  "31": "Qusjdvjfbd",
  "32": "Irsjdvgrvb",
  "33": "Qsjavnfbdb",
  "34": "Wjsjfnsla",
  "35": "Rjshebfjs",
  "36": "Oshjdbfjs",
  "37": "Psjdhvfns",
  "38": "Ahsjdnfnb",
  "39": "Sjsjdnfnvb",
  "40": "Djsjfnsjf",
  "41": "Fjsjdnsjd",
  "42": "Gjsjdnsjd",
  "43": "Hjsjdnsjd",
  "44": "Jsjsjfnsd",
  "45": "Ksjsjdnsd",
  "46": "Lsjsjdnsd",
  "47": "Zsjsjdnsd",
  "48": "Xsjsjdnsd",
  "49": "Csjsjdnsd",
  "50": "Vsjsjdnsd",
  "51": "Bsjsjdnsd",
  "52": "Nsjsjdnsd",
  "53": "Msjsjdnsd",
  "54": "Ajsjsjdsd",
  "55": "Sjsjsjdsd",
  "56": "Djsjsjdsd",
  "57": "Fjsjsjdsd",
  "58": "Gjsjsjdsd",
  "59": "Hjsjsjdsd",
  "60": "Jksjsjdsd",
  "61": "Klsjsjdsd",
  "62": "Lmsjsjdsd",
  "63": "Znsjsjdsd",
  "64": "Xosjsjdsd",
  "65": "Cpsjsjdsd",
  "66": "Vqsjsjdsd",
  "67": "Brsjsjdsd",
  "68": "Nssjsjdsd",
  "69": "Mtsjsjdsd",
  "70": "Ausjsjdsd",
  "71": "Svsjsjdsd",
  "72": "Dwsjsjdsd",
  "73": "Fxsjsjdsd",
  "74": "Gysjsjdsd",
  "75": "Hzsjsjdsd",
  "76": "Jasjsjdsd",
  "77": "Kbsjsjdsd",
  "78": "Lcsjsjdsd",
  "79": "Zdsjsjdsd",
  "80": "Xesjsjdsd",
  "81": "Cfsjsjdsd",
  "82": "Vgsjsjdsd",
  "83": "Bhsjsjdsd",
  "84": "Nisjsjdsd",
  "85": "Mjsjsjdsd",
  "86": "Aksjsjdsd",
  "87": "Slsjsjdsd",
  "88": "Dmsjsjdsd",
  "89": "Fnsjsjdsd",
  "90": "Gosjsjdsd",
  "91": "Hpsjsjdsd",
  "92": "Jqsjsjdsd",
  "93": "Krsjsjdsd",
  "94": "Lssjsjdsd",
  "95": "Ztsjsjdsd",
  "96": "Xusjsjdsd",
  "97": "Cvsjsjdsd",
  "98": "Vwsjsjdsd",
  "99": "Bxsjsjdsd",
  "100": "Nysjsjdsd",
  "101": "Mzsjsjdsd",
  "102": "Aasjsjdsd",
  "103": "Sbsjsjdsd",
  "104": "Dcsjsjdsd",
  "105": "Fdsjsjdsd",
  "106": "Gesjsjdsd",
  "107": "Hfsjsjdsd",
  "108": "Jgsjsjdsd",
  "109": "Khsjsjdsd",
  "110": "Lisjsjdsd",
  "111": "Zjsjsjdsd",
  "112": "Xksjsjdsd",
  "113": "Clsjsjdsd",
  "114": "Vmsjsjdsd",
  "115": "Bnsjsjdsd",
  "116": "Nosjsjdsd",
  "117": "Mpsjsjdsd",
  "118": "Aqsjsjdsd",
  "119": "Srsjsjdsd",
  "120": "Dssjsjdsd",
  "121": "Ftsjsjdsd",
  "122": "Gusjsjdsd",
  "123": "Hvsjsjdsd",
  "124": "Jwsjsjdsd",
  "125": "Kxsjsjdsd",
  "126": "Lysjsjdsd",
  "127": "Zzsjsjdsd",
  "128": "Xaasjdsd",
  "129": "Cabsjdsd",
  "130": "Vacsjdsd",
  "131": "Badsjdsd",
  "132": "Naesjdsd",
  "133": "Mafsjdsd",
  "134": "Aagsjdsd",
  "135": "Sahsjdsd",
  "136": "Daijsdsd",
  "137": "Fajksdsd",
  "138": "Galsdsd",
  "139": "Hamsdsd",
  "140": "Jansdsd",
  "141": "Kaosdsd",
  "142": "Lapsdsd",
  "143": "Zaqsdsd",
  "144": "Xarsdsd",
  "145": "Cassdsd",
  "146": "Vatsdsd",
  "147": "Bausdsd",
  "148": "Navsdsd",
  "149": "Mawsdsd",
  "150": "Aaxsdsd",
  "151": "Saysdsd",
  "152": "Dazsdsd",
  "153": "Fbasdsd",
  "154": "Gbbsdsd",
  "155": "Hbcsdsd",
  "156": "Jbdsdsd",
  "157": "Kbesdsd",
  "158": "Lbfsdsd",
  "159": "Zbgsdsd",
  "160": "Xbhsdsd",
  "161": "Cbisdsd",
  "162": "Vbjsdsd",
  "163": "Bbksdsd",
  "164": "Nblsdsd",
  "165": "Mbmsdsd",
  "166": "Abnsdsd",
  "167": "Sbosdsd",
  "168": "Dbpsdsd",
  "169": "Fbqsdsd",
  "170": "Gbrsdsd",
  "171": "Hbssdsd",
  "172": "Jbtsdsd",
  "173": "Kbusdsd",
  "174": "Lbvsdsd",
  "175": "Zbwsdsd",
  "176": "Xbxsdsd",
  "177": "Cbysdsd",
  "178": "Vbzsdsd",
  "179": "Bcasdsd",
  "180": "Ncbsdsd",
  "181": "Mccsdsd",
  "182": "Acdsdsd",
  "183": "Scesdsd",
  "184": "Dcfsdsd",
  "185": "Fcgsdsd",
  "186": "Gchsdsd",
  "187": "Hcisdsd",
  "188": "Jcjsdsd",
  "189": "Kcksdsd",
  "190": "Lclsdsd",
  "191": "Zcmsdsd",
  "192": "Xcnsdsd",
  "193": "Ccosdsd",
  "194": "Vcpsdsd",
  "195": "Bcqsdsd",
  "196": "Ncrsdsd",
  "197": "Mcssdsd",
  "198": "Actsdsd",
  "199": "Scusdsd",
  "200": "Dcvsdsd",
  "201": "Fcwsdsd",
  "202": "Gcxsdsd",
  "203": "Hcysdsd",
  "204": "Jczsdsd",
  "205": "Kdasdsd",
  "206": "Ldbsdsd",
  "207": "Zdcsdsd",
  "208": "Xddsdsd",
  "209": "Cdesdsd",
  "210": "Vdfsdsd",
  "211": "Bdgsdsd",
  "212": "Ndhsdsd",
  "213": "Mdisdsd",
  "214": "Adjsdsd",
  "215": "Sdksdsd",
  "216": "Ddlsdsd",
  "217": "Fdmsdsd",
  "218": "Gdnsdsd",
  "219": "Hdosdsd",
  "220": "Jdpsdsd",
  "221": "Kdqsdsd",
  "222": "Ldrsdsd",
  "223": "Zdssdsd",
  "224": "Xdtsdsd",
  "225": "Cdusdsd",
  "226": "Vdvsdsd",
  "227": "Bdwsdsd",
  "228": "Ndxsdsd",
  "229": "Mdysdsd",
  "230": "Adzsdsd",
  "231": "Seasdsd",
  "232": "Debsdsd",
  "233": "Fecsdsd",
  "234": "Gedsdsd",
  "235": "Heesdsd",
  "236": "Jefsdsd",
  "237": "Kegsdsd",
  "238": "Lehsdsd",
  "239": "Zeisdsd",
  "240": "Xejsdsd",
  "241": "Ceksdsd",
  "242": "Velsdsd",
  "243": "Bemsdsd",
  "244": "Nensdsd",
  "245": "Meosdsd",
  "246": "Aepsdsd",
  "247": "Seqsdsd",
  "248": "Dersdsd",
  "249": "Fessdsd",
  "250": "Getsdsd",
  "251": "Heusdsd",
  "252": "Jevsdsd",
  "253": "Kewsdsd",
  "254": "Lexsdsd",
  "255": "Umirpaiya"
}
